djangojs/__init__.py
djangojs/conf.py
djangojs/context_processors.py
djangojs/context_serializer.py
djangojs/models.py
djangojs/runners.py
djangojs/settings.py
djangojs/tap.py
djangojs/test_urls.py
djangojs/urls.py
djangojs/urls_serializer.py
djangojs/utils.py
djangojs/views.py
djangojs/wsgi.py
djangojs/contrib/__init__.py
djangojs/contrib/social_auth.py
djangojs/fake/__init__.py
djangojs/fake/models.py
djangojs/fake/locale/en/LC_MESSAGES/djangojs.po
djangojs/locale/en/LC_MESSAGES/djangojs.po
djangojs/locale/fr/LC_MESSAGES/djangojs.po
djangojs/management/__init__.py
djangojs/management/commands/__init__.py
djangojs/management/commands/js.py
djangojs/management/commands/js_bower.py
djangojs/management/commands/js_launcher.py
djangojs/management/commands/js_localize.py
djangojs/management/commands/subparser.py
djangojs/phantomjs/jasmine-runner.js
djangojs/phantomjs/qunit-runner.js
djangojs/static/js/djangojs/django.js
djangojs/static/js/djangojs/django.min.js
djangojs/static/js/libs/jquery-1.10.1.js
djangojs/static/js/libs/jquery-1.10.1.min.js
djangojs/static/js/libs/jquery-1.10.2.js
djangojs/static/js/libs/jquery-1.10.2.min.js
djangojs/static/js/libs/jquery-1.8.3.js
djangojs/static/js/libs/jquery-1.8.3.min.js
djangojs/static/js/libs/jquery-1.9.0.js
djangojs/static/js/libs/jquery-1.9.0.min.js
djangojs/static/js/libs/jquery-1.9.1.js
djangojs/static/js/libs/jquery-1.9.1.min.js
djangojs/static/js/libs/jquery-2.0.0.js
djangojs/static/js/libs/jquery-2.0.0.min.js
djangojs/static/js/libs/jquery-2.0.1.js
djangojs/static/js/libs/jquery-2.0.1.min.js
djangojs/static/js/libs/jquery-2.0.2.js
djangojs/static/js/libs/jquery-2.0.2.min.js
djangojs/static/js/libs/jquery-2.0.3.js
djangojs/static/js/libs/jquery-2.0.3.min.js
djangojs/static/js/libs/jquery-migrate-1.0.0.min.js
djangojs/static/js/libs/jquery-migrate-1.1.0.js
djangojs/static/js/libs/jquery-migrate-1.1.1.js
djangojs/static/js/libs/jquery-migrate-1.1.1.min.js
djangojs/static/js/libs/jquery-migrate-1.2.0.js
django.js_ng-2.4.0.dist-info/LICENSE
django.js_ng-2.4.0.dist-info/METADATA
django.js_ng-2.4.0.dist-info/WHEEL
django.js_ng-2.4.0.dist-info/top_level.txt
django.js_ng-2.4.0.dist-info/RECORD
