Metadata-Version: 2.1
Name: django.js-ng
Version: 2.4.0
Summary: Django JS Tools
Home-page: https://github.com/Robert-Chiang/django.js
Download-URL: http://pypi.python.org/pypi/django.js-ng
Author: Robert Chiang
Author-email: robert@streetvoice.com
License: LGPL
Keywords: django javascript test url reverse helpers
Classifier: Framework :: Django
Classifier: Development Status :: 4 - Beta
Classifier: Programming Language :: Python
Classifier: Environment :: Web Environment
Classifier: Operating System :: OS Independent
Classifier: Intended Audience :: Developers
Classifier: Topic :: System :: Software Distribution
Classifier: Programming Language :: Python
Classifier: Programming Language :: Python :: 3
Classifier: Topic :: Software Development :: Libraries :: Python Modules
Classifier: License :: OSI Approved :: GNU Library or Lesser General Public License (LGPL)
License-File: LICENSE
Requires-Dist: django
